{
  "profile_key": "1951506111",
  "aliases": [
    "1951506111",
    "Whoopylicious"
  ],
  "username": "Whoopylicious",
  "user_id": 1951506111,
  "avatar_url": "assets/avatars/1951506111.png",
  "profile_url": "https://www.roblox.com/users/1951506111/profile",
  "total_battles": 1,
  "latest_rank": 29,
  "latest_points": 749980,
  "latest_seen": "2026-05-11T18:00:00.000Z",
  "battles": [
    {
      "battle": "Safety Battle",
      "display_name": "Safety Battle",
      "battle_first_snapshot": "2026-05-11T18:00:00.000Z",
      "battle_last_snapshot": "2026-05-11T18:00:00.000Z",
      "first_seen": "2026-05-11T18:00:00.000Z",
      "first_active_date": "2026-05-11T18:00:00.000Z",
      "last_seen": "2026-05-11T18:00:00.000Z",
      "starting_rank": 29,
      "last_rank": 29,
      "end_rank": 29,
      "best_rank": 29,
      "worst_rank": 29,
      "starting_points": 749980,
      "ending_points": 749980,
      "max_points": 749980,
      "gained_points": 0,
      "snapshot_count": 1,
      "present_at_final_snapshot": true,
      "note": null,
      "series": [
        {
          "t": "2026-05-11T18:00:00.000Z",
          "rank": 29,
          "points": 749980
        }
      ]
    }
  ]
}
