{
  "profile_key": "3847249307",
  "aliases": [
    "3847249307",
    "Ewan_315"
  ],
  "username": "Ewan_315",
  "user_id": 3847249307,
  "avatar_url": null,
  "profile_url": "https://www.roblox.com/users/3847249307/profile",
  "total_battles": 1,
  "latest_rank": 71,
  "latest_points": 12000,
  "latest_seen": "2026-05-13T14:36:22.748Z",
  "battles": [
    {
      "battle": "AngelBattle2026",
      "display_name": "Angel Battle 2026",
      "battle_first_snapshot": "2026-05-11T14:23:36.089Z",
      "battle_last_snapshot": "2026-05-13T14:36:22.748Z",
      "first_seen": "2026-05-13T14:06:18.924Z",
      "first_active_date": "2026-05-13T14:06:18.924Z",
      "last_seen": "2026-05-13T14:36:22.748Z",
      "starting_rank": 70,
      "last_rank": 71,
      "end_rank": 71,
      "best_rank": 70,
      "worst_rank": 71,
      "starting_points": 12000,
      "ending_points": 12000,
      "max_points": 12000,
      "gained_points": 0,
      "snapshot_count": 7,
      "present_at_final_snapshot": true,
      "note": null,
      "series": [
        {
          "t": "2026-05-13T14:06:18.924Z",
          "rank": 70,
          "points": 12000
        },
        {
          "t": "2026-05-13T14:11:20.488Z",
          "rank": 70,
          "points": 12000
        },
        {
          "t": "2026-05-13T14:16:19.778Z",
          "rank": 70,
          "points": 12000
        },
        {
          "t": "2026-05-13T14:21:18.826Z",
          "rank": 71,
          "points": 12000
        },
        {
          "t": "2026-05-13T14:26:18.246Z",
          "rank": 71,
          "points": 12000
        },
        {
          "t": "2026-05-13T14:31:30.586Z",
          "rank": 71,
          "points": 12000
        },
        {
          "t": "2026-05-13T14:36:22.748Z",
          "rank": 71,
          "points": 12000
        }
      ]
    }
  ]
}
