{
  "generated_at": "2026-05-01T16:21:44.683Z",
  "snapshot_at": "2026-05-01T16:21:00.711Z",
  "battle": "StarryBattle",
  "display_name": "Starry Battle",
  "battle_end_iso": "2026-05-02T14:00:00Z",
  "clan_name": "NONG",
  "clan_rank": 29,
  "clan_points": 520054,
  "projected_rank": 26,
  "projected_points": 636593,
  "projection_basis": "12h",
  "hours_remaining": 21.65,
  "rows": [
    {
      "rank": 1,
      "clan_name": "UN0",
      "points": 968427,
      "gain_5m": 615,
      "gain_1h": 7304,
      "gain_12h": 88059,
      "gain_24h": null,
      "rate_per_hour": 7338.25,
      "projection_basis": "12h",
      "projected_points": 1127299,
      "fetched_at": "2026-05-01T16:21:00.711+00:00",
      "projected_rank": 1
    },
    {
      "rank": 2,
      "clan_name": "RFIL",
      "points": 921674,
      "gain_5m": 582,
      "gain_1h": 7317,
      "gain_12h": 86578,
      "gain_24h": null,
      "rate_per_hour": 7214.833333333333,
      "projection_basis": "12h",
      "projected_points": 1077874,
      "fetched_at": "2026-05-01T16:21:00.711+00:00",
      "projected_rank": 2
    },
    {
      "rank": 3,
      "clan_name": "SOPU",
      "points": 915029,
      "gain_5m": 590,
      "gain_1h": 7152,
      "gain_12h": 86927,
      "gain_24h": null,
      "rate_per_hour": 7243.916666666667,
      "projection_basis": "12h",
      "projected_points": 1071858,
      "fetched_at": "2026-05-01T16:21:00.711+00:00",
      "projected_rank": 3
    },
    {
      "rank": 4,
      "clan_name": "BOSS",
      "points": 831498,
      "gain_5m": 549,
      "gain_1h": 6958,
      "gain_12h": 78224,
      "gain_24h": null,
      "rate_per_hour": 6518.666666666667,
      "projection_basis": "12h",
      "projected_points": 972626,
      "fetched_at": "2026-05-01T16:21:00.711+00:00",
      "projected_rank": 4
    },
    {
      "rank": 5,
      "clan_name": "GSTG",
      "points": 821872,
      "gain_5m": 546,
      "gain_1h": 6757,
      "gain_12h": 79215,
      "gain_24h": null,
      "rate_per_hour": 6601.25,
      "projection_basis": "12h",
      "projected_points": 964788,
      "fetched_at": "2026-05-01T16:21:00.711+00:00",
      "projected_rank": 5
    },
    {
      "rank": 6,
      "clan_name": "GANG",
      "points": 786502,
      "gain_5m": 546,
      "gain_1h": 6867,
      "gain_12h": 82851,
      "gain_24h": null,
      "rate_per_hour": 6904.25,
      "projection_basis": "12h",
      "projected_points": 935978,
      "fetched_at": "2026-05-01T16:21:00.711+00:00",
      "projected_rank": 6
    },
    {
      "rank": 7,
      "clan_name": "B33Z",
      "points": 786419,
      "gain_5m": 545,
      "gain_1h": 6354,
      "gain_12h": 75525,
      "gain_24h": null,
      "rate_per_hour": 6293.75,
      "projection_basis": "12h",
      "projected_points": 922677,
      "fetched_at": "2026-05-01T16:21:00.711+00:00",
      "projected_rank": 7
    },
    {
      "rank": 8,
      "clan_name": "H8M3",
      "points": 777375,
      "gain_5m": 525,
      "gain_1h": 6735,
      "gain_12h": 79577,
      "gain_24h": null,
      "rate_per_hour": 6631.416666666667,
      "projection_basis": "12h",
      "projected_points": 920944,
      "fetched_at": "2026-05-01T16:21:00.711+00:00",
      "projected_rank": 8
    },
    {
      "rank": 9,
      "clan_name": "C0LD",
      "points": 770441,
      "gain_5m": 497,
      "gain_1h": 6320,
      "gain_12h": 76518,
      "gain_24h": null,
      "rate_per_hour": 6376.5,
      "projection_basis": "12h",
      "projected_points": 908491,
      "fetched_at": "2026-05-01T16:21:00.711+00:00",
      "projected_rank": 9
    },
    {
      "rank": 10,
      "clan_name": "POPS",
      "points": 762982,
      "gain_5m": 522,
      "gain_1h": 6609,
      "gain_12h": 76442,
      "gain_24h": null,
      "rate_per_hour": 6370.166666666667,
      "projection_basis": "12h",
      "projected_points": 900895,
      "fetched_at": "2026-05-01T16:21:00.711+00:00",
      "projected_rank": 11
    },
    {
      "rank": 11,
      "clan_name": "minx",
      "points": 753993,
      "gain_5m": 538,
      "gain_1h": 6596,
      "gain_12h": 82065,
      "gain_24h": null,
      "rate_per_hour": 6838.75,
      "projection_basis": "12h",
      "projected_points": 902051,
      "fetched_at": "2026-05-01T16:21:00.711+00:00",
      "projected_rank": 10
    },
    {
      "rank": 12,
      "clan_name": "3zEZ",
      "points": 724208,
      "gain_5m": 480,
      "gain_1h": 5968,
      "gain_12h": 71118,
      "gain_24h": null,
      "rate_per_hour": 5926.5,
      "projection_basis": "12h",
      "projected_points": 852516,
      "fetched_at": "2026-05-01T16:21:00.711+00:00",
      "projected_rank": 12
    },
    {
      "rank": 13,
      "clan_name": "K0ii",
      "points": 721733,
      "gain_5m": 468,
      "gain_1h": 6016,
      "gain_12h": 64339,
      "gain_24h": null,
      "rate_per_hour": 5361.583333333333,
      "projection_basis": "12h",
      "projected_points": 837810,
      "fetched_at": "2026-05-01T16:21:00.711+00:00",
      "projected_rank": 13
    },
    {
      "rank": 14,
      "clan_name": "DGSL",
      "points": 680397,
      "gain_5m": 438,
      "gain_1h": 5434,
      "gain_12h": 68708,
      "gain_24h": null,
      "rate_per_hour": 5725.666666666667,
      "projection_basis": "12h",
      "projected_points": 804357,
      "fetched_at": "2026-05-01T16:21:00.711+00:00",
      "projected_rank": 14
    },
    {
      "rank": 15,
      "clan_name": "_MGW",
      "points": 653685,
      "gain_5m": 480,
      "gain_1h": 6081,
      "gain_12h": 76273,
      "gain_24h": null,
      "rate_per_hour": 6356.083333333333,
      "projection_basis": "12h",
      "projected_points": 791293,
      "fetched_at": "2026-05-01T16:21:00.711+00:00",
      "projected_rank": 15
    },
    {
      "rank": 16,
      "clan_name": "H8ER",
      "points": 652355,
      "gain_5m": 470,
      "gain_1h": 5535,
      "gain_12h": 68987,
      "gain_24h": null,
      "rate_per_hour": 5748.916666666667,
      "projection_basis": "12h",
      "projected_points": 776818,
      "fetched_at": "2026-05-01T16:21:00.711+00:00",
      "projected_rank": 16
    },
    {
      "rank": 17,
      "clan_name": "VPT0",
      "points": 640346,
      "gain_5m": 421,
      "gain_1h": 5561,
      "gain_12h": 62844,
      "gain_24h": null,
      "rate_per_hour": 5237,
      "projection_basis": "12h",
      "projected_points": 753726,
      "fetched_at": "2026-05-01T16:21:00.711+00:00",
      "projected_rank": 17
    },
    {
      "rank": 18,
      "clan_name": "KOHV",
      "points": 620402,
      "gain_5m": 341,
      "gain_1h": 4427,
      "gain_12h": 52284,
      "gain_24h": null,
      "rate_per_hour": 4357,
      "projection_basis": "12h",
      "projected_points": 714730,
      "fetched_at": "2026-05-01T16:21:00.711+00:00",
      "projected_rank": 20
    },
    {
      "rank": 19,
      "clan_name": "M4RB",
      "points": 606880,
      "gain_5m": 369,
      "gain_1h": 4819,
      "gain_12h": 60581,
      "gain_24h": null,
      "rate_per_hour": 5048.416666666667,
      "projection_basis": "12h",
      "projected_points": 716177,
      "fetched_at": "2026-05-01T16:21:00.711+00:00",
      "projected_rank": 18
    },
    {
      "rank": 20,
      "clan_name": "TPGD",
      "points": 604576,
      "gain_5m": 424,
      "gain_1h": 5018,
      "gain_12h": 61293,
      "gain_24h": null,
      "rate_per_hour": 5107.75,
      "projection_basis": "12h",
      "projected_points": 715158,
      "fetched_at": "2026-05-01T16:21:00.711+00:00",
      "projected_rank": 19
    },
    {
      "rank": 21,
      "clan_name": "RY0",
      "points": 589809,
      "gain_5m": 361,
      "gain_1h": 2080,
      "gain_12h": 55352,
      "gain_24h": null,
      "rate_per_hour": 4612.666666666667,
      "projection_basis": "12h",
      "projected_points": 689672,
      "fetched_at": "2026-05-01T16:21:00.711+00:00",
      "projected_rank": 22
    },
    {
      "rank": 22,
      "clan_name": "0RBI",
      "points": 587064,
      "gain_5m": 437,
      "gain_1h": 5593,
      "gain_12h": 64184,
      "gain_24h": null,
      "rate_per_hour": 5348.666666666667,
      "projection_basis": "12h",
      "projected_points": 702862,
      "fetched_at": "2026-05-01T16:21:00.711+00:00",
      "projected_rank": 21
    },
    {
      "rank": 23,
      "clan_name": "XB0X",
      "points": 574871,
      "gain_5m": 316,
      "gain_1h": 3897,
      "gain_12h": 46976,
      "gain_24h": null,
      "rate_per_hour": 3914.6666666666665,
      "projection_basis": "12h",
      "projected_points": 659623,
      "fetched_at": "2026-05-01T16:21:00.711+00:00",
      "projected_rank": 24
    },
    {
      "rank": 24,
      "clan_name": "YLW",
      "points": 568264,
      "gain_5m": 406,
      "gain_1h": 4917,
      "gain_12h": 61081,
      "gain_24h": null,
      "rate_per_hour": 5090.083333333333,
      "projection_basis": "12h",
      "projected_points": 678463,
      "fetched_at": "2026-05-01T16:21:00.711+00:00",
      "projected_rank": 23
    },
    {
      "rank": 25,
      "clan_name": "UNTY",
      "points": 548870,
      "gain_5m": 385,
      "gain_1h": 4459,
      "gain_12h": 55720,
      "gain_24h": null,
      "rate_per_hour": 4643.333333333333,
      "projection_basis": "12h",
      "projected_points": 649397,
      "fetched_at": "2026-05-01T16:21:00.711+00:00",
      "projected_rank": 25
    },
    {
      "rank": 26,
      "clan_name": "OSTN",
      "points": 536185,
      "gain_5m": 323,
      "gain_1h": 4527,
      "gain_12h": 47050,
      "gain_24h": null,
      "rate_per_hour": 3920.8333333333335,
      "projection_basis": "12h",
      "projected_points": 621070,
      "fetched_at": "2026-05-01T16:21:00.711+00:00",
      "projected_rank": 27
    },
    {
      "rank": 27,
      "clan_name": "st1z",
      "points": 527299,
      "gain_5m": 344,
      "gain_1h": 4317,
      "gain_12h": 46021,
      "gain_24h": null,
      "rate_per_hour": 3835.0833333333335,
      "projection_basis": "12h",
      "projected_points": 610328,
      "fetched_at": "2026-05-01T16:21:00.711+00:00",
      "projected_rank": 31
    },
    {
      "rank": 28,
      "clan_name": "PsAG",
      "points": 523096,
      "gain_5m": 374,
      "gain_1h": 4722,
      "gain_12h": 50684,
      "gain_24h": null,
      "rate_per_hour": 4223.666666666667,
      "projection_basis": "12h",
      "projected_points": 614538,
      "fetched_at": "2026-05-01T16:21:00.711+00:00",
      "projected_rank": 30
    },
    {
      "rank": 29,
      "clan_name": "NONG",
      "points": 520054,
      "gain_5m": 404,
      "gain_1h": 5367,
      "gain_12h": 64595,
      "gain_24h": null,
      "rate_per_hour": 5382.916666666667,
      "projection_basis": "12h",
      "projected_points": 636593,
      "fetched_at": "2026-05-01T16:21:00.711+00:00",
      "projected_rank": 26
    },
    {
      "rank": 30,
      "clan_name": "dace",
      "points": 511319,
      "gain_5m": 417,
      "gain_1h": 5065,
      "gain_12h": 58156,
      "gain_24h": null,
      "rate_per_hour": 4846.333333333333,
      "projection_basis": "12h",
      "projected_points": 616241,
      "fetched_at": "2026-05-01T16:21:00.711+00:00",
      "projected_rank": 29
    },
    {
      "rank": 31,
      "clan_name": "W2VY",
      "points": 509972,
      "gain_5m": 401,
      "gain_1h": 4529,
      "gain_12h": 50436,
      "gain_24h": null,
      "rate_per_hour": 4203,
      "projection_basis": "12h",
      "projected_points": 600966,
      "fetched_at": "2026-05-01T16:21:00.711+00:00",
      "projected_rank": 32
    },
    {
      "rank": 32,
      "clan_name": "HSTL",
      "points": 508807,
      "gain_5m": 422,
      "gain_1h": 5237,
      "gain_12h": 61799,
      "gain_24h": null,
      "rate_per_hour": 5149.916666666667,
      "projection_basis": "12h",
      "projected_points": 620302,
      "fetched_at": "2026-05-01T16:21:00.711+00:00",
      "projected_rank": 28
    },
    {
      "rank": 33,
      "clan_name": "KRR",
      "points": 489490,
      "gain_5m": 356,
      "gain_1h": 4523,
      "gain_12h": 53455,
      "gain_24h": null,
      "rate_per_hour": 4454.583333333333,
      "projection_basis": "12h",
      "projected_points": 585931,
      "fetched_at": "2026-05-01T16:21:00.711+00:00",
      "projected_rank": 33
    },
    {
      "rank": 34,
      "clan_name": "EDS1",
      "points": 482249,
      "gain_5m": 327,
      "gain_1h": 3971,
      "gain_12h": 49513,
      "gain_24h": null,
      "rate_per_hour": 4126.083333333333,
      "projection_basis": "12h",
      "projected_points": 571578,
      "fetched_at": "2026-05-01T16:21:00.711+00:00",
      "projected_rank": 34
    },
    {
      "rank": 35,
      "clan_name": "L1GO",
      "points": 461207,
      "gain_5m": 325,
      "gain_1h": 3680,
      "gain_12h": 43032,
      "gain_24h": null,
      "rate_per_hour": 3586,
      "projection_basis": "12h",
      "projected_points": 538843,
      "fetched_at": "2026-05-01T16:21:00.711+00:00",
      "projected_rank": 39
    },
    {
      "rank": 36,
      "clan_name": "DV_",
      "points": 461192,
      "gain_5m": 337,
      "gain_1h": 3994,
      "gain_12h": 47055,
      "gain_24h": null,
      "rate_per_hour": 3921.25,
      "projection_basis": "12h",
      "projected_points": 546086,
      "fetched_at": "2026-05-01T16:21:00.711+00:00",
      "projected_rank": 37
    },
    {
      "rank": 37,
      "clan_name": "Taux",
      "points": 458106,
      "gain_5m": 414,
      "gain_1h": 5088,
      "gain_12h": 59112,
      "gain_24h": null,
      "rate_per_hour": 4926,
      "projection_basis": "12h",
      "projected_points": 564753,
      "fetched_at": "2026-05-01T16:21:00.711+00:00",
      "projected_rank": 35
    },
    {
      "rank": 38,
      "clan_name": "V1LN",
      "points": 455621,
      "gain_5m": 164,
      "gain_1h": 2106,
      "gain_12h": 26827,
      "gain_24h": null,
      "rate_per_hour": 2235.5833333333335,
      "projection_basis": "12h",
      "projected_points": 504021,
      "fetched_at": "2026-05-01T16:21:00.711+00:00",
      "projected_rank": 41
    },
    {
      "rank": 39,
      "clan_name": "OLDD",
      "points": 455360,
      "gain_5m": 397,
      "gain_1h": 4545,
      "gain_12h": 49375,
      "gain_24h": null,
      "rate_per_hour": 4114.583333333333,
      "projection_basis": "12h",
      "projected_points": 544440,
      "fetched_at": "2026-05-01T16:21:00.711+00:00",
      "projected_rank": 38
    },
    {
      "rank": 40,
      "clan_name": "blkl",
      "points": 443208,
      "gain_5m": 396,
      "gain_1h": 4823,
      "gain_12h": 57925,
      "gain_24h": null,
      "rate_per_hour": 4827.083333333333,
      "projection_basis": "12h",
      "projected_points": 547713,
      "fetched_at": "2026-05-01T16:21:00.711+00:00",
      "projected_rank": 36
    },
    {
      "rank": 41,
      "clan_name": "7HRW",
      "points": 440558,
      "gain_5m": 302,
      "gain_1h": 3891,
      "gain_12h": 46667,
      "gain_24h": null,
      "rate_per_hour": 3888.9166666666665,
      "projection_basis": "12h",
      "projected_points": 524752,
      "fetched_at": "2026-05-01T16:21:00.711+00:00",
      "projected_rank": 40
    },
    {
      "rank": 42,
      "clan_name": "FNXX",
      "points": 421709,
      "gain_5m": 321,
      "gain_1h": 4059,
      "gain_12h": 44794,
      "gain_24h": null,
      "rate_per_hour": 3732.8333333333335,
      "projection_basis": "12h",
      "projected_points": 502524,
      "fetched_at": "2026-05-01T16:21:00.711+00:00",
      "projected_rank": 43
    },
    {
      "rank": 43,
      "clan_name": "TLGZ",
      "points": 420283,
      "gain_5m": 324,
      "gain_1h": 3797,
      "gain_12h": 46018,
      "gain_24h": null,
      "rate_per_hour": 3834.8333333333335,
      "projection_basis": "12h",
      "projected_points": 503306,
      "fetched_at": "2026-05-01T16:21:00.711+00:00",
      "projected_rank": 42
    },
    {
      "rank": 44,
      "clan_name": "GCEM",
      "points": 417452,
      "gain_5m": 317,
      "gain_1h": 3747,
      "gain_12h": 38998,
      "gain_24h": null,
      "rate_per_hour": 3249.8333333333335,
      "projection_basis": "12h",
      "projected_points": 487810,
      "fetched_at": "2026-05-01T16:21:00.711+00:00",
      "projected_rank": 47
    },
    {
      "rank": 45,
      "clan_name": "FGZW",
      "points": 409075,
      "gain_5m": 276,
      "gain_1h": 3482,
      "gain_12h": 40669,
      "gain_24h": null,
      "rate_per_hour": 3389.0833333333335,
      "projection_basis": "12h",
      "projected_points": 482448,
      "fetched_at": "2026-05-01T16:21:00.711+00:00",
      "projected_rank": 48
    },
    {
      "rank": 46,
      "clan_name": "FaZ",
      "points": 406079,
      "gain_5m": 327,
      "gain_1h": 4106,
      "gain_12h": 50142,
      "gain_24h": null,
      "rate_per_hour": 4178.5,
      "projection_basis": "12h",
      "projected_points": 496543,
      "fetched_at": "2026-05-01T16:21:00.711+00:00",
      "projected_rank": 44
    },
    {
      "rank": 47,
      "clan_name": "J200",
      "points": 405390,
      "gain_5m": 315,
      "gain_1h": 3733,
      "gain_12h": 39274,
      "gain_24h": null,
      "rate_per_hour": 3272.8333333333335,
      "projection_basis": "12h",
      "projected_points": 476246,
      "fetched_at": "2026-05-01T16:21:00.711+00:00",
      "projected_rank": 49
    },
    {
      "rank": 48,
      "clan_name": "4fil",
      "points": 405208,
      "gain_5m": 366,
      "gain_1h": 4280,
      "gain_12h": 46876,
      "gain_24h": null,
      "rate_per_hour": 3906.3333333333335,
      "projection_basis": "12h",
      "projected_points": 489779,
      "fetched_at": "2026-05-01T16:21:00.711+00:00",
      "projected_rank": 45
    },
    {
      "rank": 49,
      "clan_name": "y3ki",
      "points": 403240,
      "gain_5m": 353,
      "gain_1h": 4010,
      "gain_12h": 47897,
      "gain_24h": null,
      "rate_per_hour": 3991.4166666666665,
      "projection_basis": "12h",
      "projected_points": 489653,
      "fetched_at": "2026-05-01T16:21:00.711+00:00",
      "projected_rank": 46
    },
    {
      "rank": 50,
      "clan_name": "_hot",
      "points": 396055,
      "gain_5m": 322,
      "gain_1h": 3921,
      "gain_12h": 44439,
      "gain_24h": null,
      "rate_per_hour": 3703.25,
      "projection_basis": "12h",
      "projected_points": 476230,
      "fetched_at": "2026-05-01T16:21:00.711+00:00",
      "projected_rank": 50
    },
    {
      "rank": 51,
      "clan_name": "LSQ",
      "points": 390957,
      "gain_5m": 339,
      "gain_1h": 4126,
      "gain_12h": 44747,
      "gain_24h": null,
      "rate_per_hour": 3728.9166666666665,
      "projection_basis": "12h",
      "projected_points": 471687,
      "fetched_at": "2026-05-01T16:21:00.711+00:00",
      "projected_rank": 51
    },
    {
      "rank": 52,
      "clan_name": "TAAK",
      "points": 383292,
      "gain_5m": 328,
      "gain_1h": 3776,
      "gain_12h": 44083,
      "gain_24h": null,
      "rate_per_hour": 3673.5833333333335,
      "projection_basis": "12h",
      "projected_points": 462824,
      "fetched_at": "2026-05-01T16:21:00.711+00:00",
      "projected_rank": 52
    },
    {
      "rank": 53,
      "clan_name": "AWZY",
      "points": 349988,
      "gain_5m": 130,
      "gain_1h": 1682,
      "gain_12h": 21524,
      "gain_24h": null,
      "rate_per_hour": 1793.6666666666667,
      "projection_basis": "12h",
      "projected_points": 388821,
      "fetched_at": "2026-05-01T16:21:00.711+00:00",
      "projected_rank": 55
    },
    {
      "rank": 54,
      "clan_name": "ANG_",
      "points": 346722,
      "gain_5m": 163,
      "gain_1h": 1942,
      "gain_12h": 27639,
      "gain_24h": null,
      "rate_per_hour": 2303.25,
      "projection_basis": "12h",
      "projected_points": 396587,
      "fetched_at": "2026-05-01T16:21:00.711+00:00",
      "projected_rank": 54
    },
    {
      "rank": 55,
      "clan_name": "1PNX",
      "points": 337352,
      "gain_5m": 211,
      "gain_1h": 2771,
      "gain_12h": 38638,
      "gain_24h": null,
      "rate_per_hour": 3219.8333333333335,
      "projection_basis": "12h",
      "projected_points": 407061,
      "fetched_at": "2026-05-01T16:21:00.711+00:00",
      "projected_rank": 53
    },
    {
      "rank": 56,
      "clan_name": "R0MU",
      "points": 321530,
      "gain_5m": 189,
      "gain_1h": 2299,
      "gain_12h": 26925,
      "gain_24h": null,
      "rate_per_hour": 2243.75,
      "projection_basis": "12h",
      "projected_points": 370107,
      "fetched_at": "2026-05-01T16:21:00.711+00:00",
      "projected_rank": 56
    },
    {
      "rank": 57,
      "clan_name": "un0_",
      "points": 305519,
      "gain_5m": 0,
      "gain_1h": 0,
      "gain_12h": 14025,
      "gain_24h": null,
      "rate_per_hour": 1168.75,
      "projection_basis": "12h",
      "projected_points": 330822,
      "fetched_at": "2026-05-01T16:21:00.711+00:00",
      "projected_rank": 58
    },
    {
      "rank": 58,
      "clan_name": "dewp",
      "points": 288693,
      "gain_5m": 245,
      "gain_1h": 2769,
      "gain_12h": 30434,
      "gain_24h": null,
      "rate_per_hour": 2536.1666666666665,
      "projection_basis": "12h",
      "projected_points": 343601,
      "fetched_at": "2026-05-01T16:21:00.711+00:00",
      "projected_rank": 57
    },
    {
      "rank": 59,
      "clan_name": "A0S",
      "points": 282794,
      "gain_5m": 142,
      "gain_1h": 1847,
      "gain_12h": 25341,
      "gain_24h": null,
      "rate_per_hour": 2111.75,
      "projection_basis": "12h",
      "projected_points": 328513,
      "fetched_at": "2026-05-01T16:21:00.711+00:00",
      "projected_rank": 59
    },
    {
      "rank": 60,
      "clan_name": "BEZE",
      "points": 278200,
      "gain_5m": 156,
      "gain_1h": 1748,
      "gain_12h": 24388,
      "gain_24h": null,
      "rate_per_hour": 2032.3333333333333,
      "projection_basis": "12h",
      "projected_points": 322200,
      "fetched_at": "2026-05-01T16:21:00.711+00:00",
      "projected_rank": 60
    },
    {
      "rank": 61,
      "clan_name": "FMLY",
      "points": 272608,
      "gain_5m": 189,
      "gain_1h": 2400,
      "gain_12h": 27469,
      "gain_24h": null,
      "rate_per_hour": 2289.0833333333335,
      "projection_basis": "12h",
      "projected_points": 322166,
      "fetched_at": "2026-05-01T16:21:00.711+00:00",
      "projected_rank": 61
    },
    {
      "rank": 62,
      "clan_name": "CITC",
      "points": 264971,
      "gain_5m": 149,
      "gain_1h": 1759,
      "gain_12h": 21786,
      "gain_24h": null,
      "rate_per_hour": 1815.5,
      "projection_basis": "12h",
      "projected_points": 304276,
      "fetched_at": "2026-05-01T16:21:00.711+00:00",
      "projected_rank": 62
    },
    {
      "rank": 63,
      "clan_name": "BYRD",
      "points": 254711,
      "gain_5m": 140,
      "gain_1h": 1724,
      "gain_12h": 18110,
      "gain_24h": null,
      "rate_per_hour": 1509.1666666666667,
      "projection_basis": "12h",
      "projected_points": 287384,
      "fetched_at": "2026-05-01T16:21:00.711+00:00",
      "projected_rank": 66
    },
    {
      "rank": 64,
      "clan_name": "MWHO",
      "points": 254232,
      "gain_5m": 136,
      "gain_1h": 1833,
      "gain_12h": 20549,
      "gain_24h": null,
      "rate_per_hour": 1712.4166666666667,
      "projection_basis": "12h",
      "projected_points": 291305,
      "fetched_at": "2026-05-01T16:21:00.711+00:00",
      "projected_rank": 64
    },
    {
      "rank": 65,
      "clan_name": "B2ZE",
      "points": 249393,
      "gain_5m": 122,
      "gain_1h": 1606,
      "gain_12h": 15737,
      "gain_24h": null,
      "rate_per_hour": 1311.4166666666667,
      "projection_basis": "12h",
      "projected_points": 277785,
      "fetched_at": "2026-05-01T16:21:00.711+00:00",
      "projected_rank": 67
    },
    {
      "rank": 66,
      "clan_name": "K1WI",
      "points": 246718,
      "gain_5m": 158,
      "gain_1h": 2088,
      "gain_12h": 25649,
      "gain_24h": null,
      "rate_per_hour": 2137.4166666666665,
      "projection_basis": "12h",
      "projected_points": 292993,
      "fetched_at": "2026-05-01T16:21:00.711+00:00",
      "projected_rank": 63
    },
    {
      "rank": 67,
      "clan_name": "LdER",
      "points": 236167,
      "gain_5m": 191,
      "gain_1h": 2311,
      "gain_12h": 29980,
      "gain_24h": null,
      "rate_per_hour": 2498.3333333333335,
      "projection_basis": "12h",
      "projected_points": 290255,
      "fetched_at": "2026-05-01T16:21:00.711+00:00",
      "projected_rank": 65
    },
    {
      "rank": 68,
      "clan_name": "JJ07",
      "points": 235615,
      "gain_5m": 174,
      "gain_1h": 2126,
      "gain_12h": 23014,
      "gain_24h": null,
      "rate_per_hour": 1917.8333333333333,
      "projection_basis": "12h",
      "projected_points": 277136,
      "fetched_at": "2026-05-01T16:21:00.711+00:00",
      "projected_rank": 68
    },
    {
      "rank": 69,
      "clan_name": "OLLY",
      "points": 227238,
      "gain_5m": 167,
      "gain_1h": 2199,
      "gain_12h": 26957,
      "gain_24h": null,
      "rate_per_hour": 2246.4166666666665,
      "projection_basis": "12h",
      "projected_points": 275872,
      "fetched_at": "2026-05-01T16:21:00.711+00:00",
      "projected_rank": 69
    },
    {
      "rank": 70,
      "clan_name": "BOSK",
      "points": 219061,
      "gain_5m": 155,
      "gain_1h": 1776,
      "gain_12h": 21034,
      "gain_24h": null,
      "rate_per_hour": 1752.8333333333333,
      "projection_basis": "12h",
      "projected_points": 257009,
      "fetched_at": "2026-05-01T16:21:00.711+00:00",
      "projected_rank": 70
    },
    {
      "rank": 71,
      "clan_name": "ELMC",
      "points": 209203,
      "gain_5m": 120,
      "gain_1h": 1413,
      "gain_12h": 12691,
      "gain_24h": null,
      "rate_per_hour": 1057.5833333333333,
      "projection_basis": "12h",
      "projected_points": 232099,
      "fetched_at": "2026-05-01T16:21:00.711+00:00",
      "projected_rank": 74
    },
    {
      "rank": 72,
      "clan_name": "ttsh",
      "points": 205432,
      "gain_5m": 181,
      "gain_1h": 1972,
      "gain_12h": 23585,
      "gain_24h": null,
      "rate_per_hour": 1965.4166666666667,
      "projection_basis": "12h",
      "projected_points": 247983,
      "fetched_at": "2026-05-01T16:21:00.711+00:00",
      "projected_rank": 71
    },
    {
      "rank": 73,
      "clan_name": "Gaea",
      "points": 204296,
      "gain_5m": 158,
      "gain_1h": 1748,
      "gain_12h": 20150,
      "gain_24h": null,
      "rate_per_hour": 1679.1666666666667,
      "projection_basis": "12h",
      "projected_points": 240650,
      "fetched_at": "2026-05-01T16:21:00.711+00:00",
      "projected_rank": 72
    },
    {
      "rank": 74,
      "clan_name": "NREG",
      "points": 197962,
      "gain_5m": 120,
      "gain_1h": 1602,
      "gain_12h": 21952,
      "gain_24h": null,
      "rate_per_hour": 1829.3333333333333,
      "projection_basis": "12h",
      "projected_points": 237567,
      "fetched_at": "2026-05-01T16:21:00.711+00:00",
      "projected_rank": 73
    },
    {
      "rank": 75,
      "clan_name": "BRWZ",
      "points": 197333,
      "gain_5m": 99,
      "gain_1h": 1245,
      "gain_12h": 15648,
      "gain_24h": null,
      "rate_per_hour": 1304,
      "projection_basis": "12h",
      "projected_points": 225564,
      "fetched_at": "2026-05-01T16:21:00.711+00:00",
      "projected_rank": 76
    },
    {
      "rank": 76,
      "clan_name": "EVOL",
      "points": 193088,
      "gain_5m": 123,
      "gain_1h": 1718,
      "gain_12h": 18818,
      "gain_24h": null,
      "rate_per_hour": 1568.1666666666667,
      "projection_basis": "12h",
      "projected_points": 227038,
      "fetched_at": "2026-05-01T16:21:00.711+00:00",
      "projected_rank": 75
    },
    {
      "rank": 77,
      "clan_name": "RGCN",
      "points": 183664,
      "gain_5m": 33,
      "gain_1h": 383,
      "gain_12h": 6220,
      "gain_24h": null,
      "rate_per_hour": 518.3333333333334,
      "projection_basis": "12h",
      "projected_points": 194886,
      "fetched_at": "2026-05-01T16:21:00.711+00:00",
      "projected_rank": 86
    },
    {
      "rank": 78,
      "clan_name": "LXCC",
      "points": 182652,
      "gain_5m": 58,
      "gain_1h": 678,
      "gain_12h": 7386,
      "gain_24h": null,
      "rate_per_hour": 615.5,
      "projection_basis": "12h",
      "projected_points": 195977,
      "fetched_at": "2026-05-01T16:21:00.711+00:00",
      "projected_rank": 82
    },
    {
      "rank": 79,
      "clan_name": "COB",
      "points": 177017,
      "gain_5m": 127,
      "gain_1h": 1629,
      "gain_12h": 20932,
      "gain_24h": null,
      "rate_per_hour": 1744.3333333333333,
      "projection_basis": "12h",
      "projected_points": 214781,
      "fetched_at": "2026-05-01T16:21:00.711+00:00",
      "projected_rank": 77
    },
    {
      "rank": 80,
      "clan_name": "Loku",
      "points": 172579,
      "gain_5m": 172,
      "gain_1h": 1834,
      "gain_12h": 20912,
      "gain_24h": null,
      "rate_per_hour": 1742.6666666666667,
      "projection_basis": "12h",
      "projected_points": 210307,
      "fetched_at": "2026-05-01T16:21:00.711+00:00",
      "projected_rank": 78
    },
    {
      "rank": 81,
      "clan_name": "3MEH",
      "points": 167928,
      "gain_5m": 122,
      "gain_1h": 1301,
      "gain_12h": 15173,
      "gain_24h": null,
      "rate_per_hour": 1264.4166666666667,
      "projection_basis": "12h",
      "projected_points": 195302,
      "fetched_at": "2026-05-01T16:21:00.711+00:00",
      "projected_rank": 85
    },
    {
      "rank": 82,
      "clan_name": "ewqe",
      "points": 167842,
      "gain_5m": 77,
      "gain_1h": 991,
      "gain_12h": 16502,
      "gain_24h": null,
      "rate_per_hour": 1375.1666666666667,
      "projection_basis": "12h",
      "projected_points": 197614,
      "fetched_at": "2026-05-01T16:21:00.711+00:00",
      "projected_rank": 80
    },
    {
      "rank": 83,
      "clan_name": "Korg",
      "points": 165800,
      "gain_5m": 102,
      "gain_1h": 1297,
      "gain_12h": 16696,
      "gain_24h": null,
      "rate_per_hour": 1391.3333333333333,
      "projection_basis": "12h",
      "projected_points": 195922,
      "fetched_at": "2026-05-01T16:21:00.711+00:00",
      "projected_rank": 83
    },
    {
      "rank": 84,
      "clan_name": "HaX4",
      "points": 164867,
      "gain_5m": 149,
      "gain_1h": 1686,
      "gain_12h": 18557,
      "gain_24h": null,
      "rate_per_hour": 1546.4166666666667,
      "projection_basis": "12h",
      "projected_points": 198347,
      "fetched_at": "2026-05-01T16:21:00.711+00:00",
      "projected_rank": 79
    },
    {
      "rank": 85,
      "clan_name": "Do1t",
      "points": 163672,
      "gain_5m": 106,
      "gain_1h": 1242,
      "gain_12h": 17571,
      "gain_24h": null,
      "rate_per_hour": 1464.25,
      "projection_basis": "12h",
      "projected_points": 195373,
      "fetched_at": "2026-05-01T16:21:00.711+00:00",
      "projected_rank": 84
    },
    {
      "rank": 86,
      "clan_name": "JKUS",
      "points": 163614,
      "gain_5m": 64,
      "gain_1h": 904,
      "gain_12h": 15510,
      "gain_24h": null,
      "rate_per_hour": 1292.5,
      "projection_basis": "12h",
      "projected_points": 191596,
      "fetched_at": "2026-05-01T16:21:00.711+00:00",
      "projected_rank": 87
    },
    {
      "rank": 87,
      "clan_name": "GST2",
      "points": 163246,
      "gain_5m": 114,
      "gain_1h": 1448,
      "gain_12h": 18743,
      "gain_24h": null,
      "rate_per_hour": 1561.9166666666667,
      "projection_basis": "12h",
      "projected_points": 197061,
      "fetched_at": "2026-05-01T16:21:00.711+00:00",
      "projected_rank": 81
    },
    {
      "rank": 88,
      "clan_name": "B3L1",
      "points": 158645,
      "gain_5m": 77,
      "gain_1h": 1142,
      "gain_12h": 17195,
      "gain_24h": null,
      "rate_per_hour": 1432.9166666666667,
      "projection_basis": "12h",
      "projected_points": 189667,
      "fetched_at": "2026-05-01T16:21:00.711+00:00",
      "projected_rank": 88
    },
    {
      "rank": 89,
      "clan_name": "Tai",
      "points": 154315,
      "gain_5m": 159,
      "gain_1h": 1603,
      "gain_12h": 15976,
      "gain_24h": null,
      "rate_per_hour": 1331.3333333333333,
      "projection_basis": "12h",
      "projected_points": 183138,
      "fetched_at": "2026-05-01T16:21:00.711+00:00",
      "projected_rank": 89
    },
    {
      "rank": 90,
      "clan_name": "eguh",
      "points": 153462,
      "gain_5m": 69,
      "gain_1h": 922,
      "gain_12h": 12691,
      "gain_24h": null,
      "rate_per_hour": 1057.5833333333333,
      "projection_basis": "12h",
      "projected_points": 176358,
      "fetched_at": "2026-05-01T16:21:00.711+00:00",
      "projected_rank": 91
    },
    {
      "rank": 91,
      "clan_name": "Winr",
      "points": 148695,
      "gain_5m": 131,
      "gain_1h": 1432,
      "gain_12h": 17740,
      "gain_24h": null,
      "rate_per_hour": 1478.3333333333333,
      "projection_basis": "12h",
      "projected_points": 180701,
      "fetched_at": "2026-05-01T16:21:00.711+00:00",
      "projected_rank": 90
    },
    {
      "rank": 92,
      "clan_name": "RMBC",
      "points": 148440,
      "gain_5m": 104,
      "gain_1h": 1425,
      "gain_12h": 11689,
      "gain_24h": null,
      "rate_per_hour": 974.0833333333334,
      "projection_basis": "12h",
      "projected_points": 169529,
      "fetched_at": "2026-05-01T16:21:00.711+00:00",
      "projected_rank": 92
    },
    {
      "rank": 93,
      "clan_name": "xpp_",
      "points": 140525,
      "gain_5m": 103,
      "gain_1h": 1188,
      "gain_12h": 15161,
      "gain_24h": null,
      "rate_per_hour": 1263.4166666666667,
      "projection_basis": "12h",
      "projected_points": 167878,
      "fetched_at": "2026-05-01T16:21:00.711+00:00",
      "projected_rank": 93
    },
    {
      "rank": 94,
      "clan_name": "ST1L",
      "points": 138436,
      "gain_5m": 99,
      "gain_1h": 1141,
      "gain_12h": 13276,
      "gain_24h": null,
      "rate_per_hour": 1106.3333333333333,
      "projection_basis": "12h",
      "projected_points": 162388,
      "fetched_at": "2026-05-01T16:21:00.711+00:00",
      "projected_rank": 99
    },
    {
      "rank": 95,
      "clan_name": "3GM6",
      "points": 138269,
      "gain_5m": 73,
      "gain_1h": 1184,
      "gain_12h": 15917,
      "gain_24h": null,
      "rate_per_hour": 1326.4166666666667,
      "projection_basis": "12h",
      "projected_points": 166986,
      "fetched_at": "2026-05-01T16:21:00.711+00:00",
      "projected_rank": 94
    },
    {
      "rank": 96,
      "clan_name": "REXW",
      "points": 138090,
      "gain_5m": 78,
      "gain_1h": 1112,
      "gain_12h": 13608,
      "gain_24h": null,
      "rate_per_hour": 1134,
      "projection_basis": "12h",
      "projected_points": 162641,
      "fetched_at": "2026-05-01T16:21:00.711+00:00",
      "projected_rank": 98
    },
    {
      "rank": 97,
      "clan_name": "Eg64",
      "points": 136078,
      "gain_5m": 93,
      "gain_1h": 1034,
      "gain_12h": 15985,
      "gain_24h": null,
      "rate_per_hour": 1332.0833333333333,
      "projection_basis": "12h",
      "projected_points": 164917,
      "fetched_at": "2026-05-01T16:21:00.711+00:00",
      "projected_rank": 95
    },
    {
      "rank": 98,
      "clan_name": "ZYXE",
      "points": 135305,
      "gain_5m": 118,
      "gain_1h": 1405,
      "gain_12h": 16098,
      "gain_24h": null,
      "rate_per_hour": 1341.5,
      "projection_basis": "12h",
      "projected_points": 164348,
      "fetched_at": "2026-05-01T16:21:00.711+00:00",
      "projected_rank": 96
    },
    {
      "rank": 99,
      "clan_name": "FTCG",
      "points": 130969,
      "gain_5m": 129,
      "gain_1h": 1529,
      "gain_12h": null,
      "gain_24h": null,
      "rate_per_hour": 1529,
      "projection_basis": "1h",
      "projected_points": 164072,
      "fetched_at": "2026-05-01T16:21:00.711+00:00",
      "projected_rank": 97
    },
    {
      "rank": 100,
      "clan_name": "AX0K",
      "points": 130234,
      "gain_5m": 106,
      "gain_1h": 1352,
      "gain_12h": null,
      "gain_24h": null,
      "rate_per_hour": 1352,
      "projection_basis": "1h",
      "projected_points": 159505,
      "fetched_at": "2026-05-01T16:21:00.711+00:00",
      "projected_rank": 100
    }
  ]
}
